<annotation>
	<folder>OTC-7</folder>
	<filename>otc7-15.jpg</filename>
	<path>E:\yanyishang\yolov5tuxiang\0707-OTC\OTC-7\otc7-15.jpg</path>
	<source>
		<database>Unknown</database>
	</source>
	<size>
		<width>694</width>
		<height>1714</height>
		<depth>3</depth>
	</size>
	<segmented>0</segmented>
	<object>
		<name>otc7</name>
		<pose>Unspecified</pose>
		<truncated>0</truncated>
		<difficult>0</difficult>
		<bndbox>
			<xmin>161</xmin>
			<ymin>223</ymin>
			<xmax>569</xmax>
			<ymax>1520</ymax>
		</bndbox>
	</object>
</annotation>
